beam_postgres/__init__.py
beam_postgres/client.py
beam_postgres/errors.py
beam_postgres/io.py
beam_postgres/source.py
beam_postgres/splitters.py
beam_postgres/utils.py
beam_postgres_connector-0.1.3.dist-info/LICENSE.txt
beam_postgres_connector-0.1.3.dist-info/METADATA
beam_postgres_connector-0.1.3.dist-info/WHEEL
beam_postgres_connector-0.1.3.dist-info/RECORD
