Metadata-Version: 2.1
Name: beam-postgres-connector
Version: 0.1.3
Summary: An io connector for PostgreSQL read/write in Apache Beam pipelines.
Home-page: https://github.com/satokiyo/beam-postgres-connector
License: MIT
Keywords: apache beam,beam,postgres,postgresql
Author: satokiyo
Author-email: satokiyo@loop8.biz
Requires-Python: >=3.8.1,<4.0.0
Classifier: License :: OSI Approved :: MIT License
Classifier: Programming Language :: Python :: 3
Classifier: Programming Language :: Python :: 3.9
Classifier: Programming Language :: Python :: 3.10
Classifier: Programming Language :: Python :: 3.11
Requires-Dist: apache-beam (>=2.46.0,<3.0.0)
Requires-Dist: poetry-dynamic-versioning (>=0.24.0,<0.25.0)
Requires-Dist: psycopg2-binary (>=2.9.6,<3.0.0)
Project-URL: Repository, https://github.com/satokiyo/beam-postgres-connector
